odoo/addons/stock_vertical_lift_server_env/README.rst
odoo/addons/stock_vertical_lift_server_env/__init__.py
odoo/addons/stock_vertical_lift_server_env/__manifest__.py
odoo/addons/stock_vertical_lift_server_env/i18n/it.po
odoo/addons/stock_vertical_lift_server_env/i18n/stock_vertical_lift_server_env.pot
odoo/addons/stock_vertical_lift_server_env/models/__init__.py
odoo/addons/stock_vertical_lift_server_env/models/vertical_lift_shuttle.py
odoo/addons/stock_vertical_lift_server_env/readme/CONTRIBUTORS.rst
odoo/addons/stock_vertical_lift_server_env/readme/CREDITS.rst
odoo/addons/stock_vertical_lift_server_env/readme/DESCRIPTION.rst
odoo/addons/stock_vertical_lift_server_env/static/description/icon.png
odoo/addons/stock_vertical_lift_server_env/static/description/index.html
odoo14_addon_stock_vertical_lift_server_env-14.0.1.0.1.dev7.dist-info/METADATA
odoo14_addon_stock_vertical_lift_server_env-14.0.1.0.1.dev7.dist-info/WHEEL
odoo14_addon_stock_vertical_lift_server_env-14.0.1.0.1.dev7.dist-info/top_level.txt
odoo14_addon_stock_vertical_lift_server_env-14.0.1.0.1.dev7.dist-info/RECORD
