Metadata-Version: 2.1
Name: odoo14-addon-stock_vertical_lift_server_env
Version: 14.0.1.0.1.dev7
Summary: Server Environment layer for Vertical Lift
Home-page: https://github.com/OCA/stock-logistics-warehouse
Author: Camptocamp, Odoo Community Association (OCA)
Author-email: support@odoo-community.org
License: AGPL-3
Classifier: Programming Language :: Python
Classifier: Framework :: Odoo
Classifier: Framework :: Odoo :: 14.0
Classifier: License :: OSI Approved :: GNU Affero General Public License v3
Classifier: Development Status :: 3 - Alpha
Requires-Python: >=3.6
Requires-Dist: odoo14-addon-server-environment
Requires-Dist: odoo14-addon-stock-vertical-lift
Requires-Dist: odoo<14.1dev,>=14.0a
